pymexc/__init__.py
pymexc/base.py
pymexc/base_websocket.py
pymexc/futures.py
pymexc/spot.py
monedadigitalm-1.0.10.post2.dist-info/LICENSE
monedadigitalm-1.0.10.post2.dist-info/METADATA
monedadigitalm-1.0.10.post2.dist-info/WHEEL
monedadigitalm-1.0.10.post2.dist-info/top_level.txt
monedadigitalm-1.0.10.post2.dist-info/RECORD
